chikvdf.cp310-win_amd64.pyd
chikvdf-1.1.14.data/platlib/mpir.dll
chikvdf-1.1.14.data/platlib/mpir_broadwell.dll
chikvdf-1.1.14.data/platlib/mpir_broadwell_avx.dll
chikvdf-1.1.14.data/platlib/mpir_bulldozer.dll
chikvdf-1.1.14.data/platlib/mpir_gc.dll
chikvdf-1.1.14.data/platlib/mpir_haswell.dll
chikvdf-1.1.14.data/platlib/mpir_piledriver.dll
chikvdf-1.1.14.data/platlib/mpir_sandybridge.dll
chikvdf-1.1.14.data/platlib/mpir_skylake_avx.dll
chikvdf-1.1.14.data/platlib/msvcp140.dll
chikvdf-1.1.14.dist-info/DELVEWHEEL
chikvdf-1.1.14.dist-info/METADATA
chikvdf-1.1.14.dist-info/RECORD
chikvdf-1.1.14.dist-info/top_level.txt
chikvdf-1.1.14.dist-info/WHEEL
chikvdf-1.1.14.dist-info/licenses/LICENSE
