Metadata-Version: 2.4
Name: chikvdf
Version: 1.1.14
Summary: Chik vdf verification (wraps C++)
Home-page: https://github.com/Chik-Network/chikvdf
Author: Florin Chirica
Author-email: florin@chiknetwork.com
License: Apache-2.0
Requires-Python: >=3.9
License-File: LICENSE
Dynamic: author
Dynamic: author-email
Dynamic: description
Dynamic: description-content-type
Dynamic: home-page
Dynamic: license
Dynamic: license-file
Dynamic: requires-python
Dynamic: summary
